{
  "todos": [
    {
      "title": "Make",
      "description": "not decided yet",
      "date": "2023-02-20",
      "priority": "High",
      "status": "Done",
      "owner": "Sid",
      "id": 19
    },
    {
      "title": "inprogress",
      "description": " hey every ",
      "date": "2023-02-22",
      "priority": "Medium",
      "status": "In-Progress",
      "owner": "Sandeep yadav",
      "id": 20
    },
    {
      "title": "Done",
      "description": "asdsafdsgdf",
      "date": "2023-02-22",
      "priority": "Low",
      "status": "In-Progress",
      "owner": "Sandeep Yadav",
      "id": 21
    },
    {
      "title": "fsdfsdgdf",
      "description": "hfhfhfgjghg",
      "date": "2023-02-22",
      "priority": "Medium",
      "status": "Done",
      "owner": "cina",
      "id": 22
    },
    {
      "title": "checking Mytask",
      "description": "Kuch bhi",
      "date": "2023-02-22",
      "priority": "High",
      "status": "Done",
      "owner": "Its ME",
      "id": 23
    },
    {
      "title": "fsfsd",
      "description": "dgdfgd",
      "date": "2023-02-22",
      "priority": "High",
      "status": "In-Progress",
      "owner": "sdfsd",
      "id": 24
    },
    {
      "title": "dgdfhgf",
      "description": "sdgdfgdfh",
      "date": "2023-02-22",
      "priority": "Medium",
      "status": "Done",
      "owner": "fsdgds",
      "id": 25
    },
    {
      "title": "Interview ",
      "description": "revision",
      "date": "2023-02-24",
      "priority": "High",
      "status": "Done",
      "owner": "Sandeep",
      "id": 26
    },
    {
      "title": "Flight",
      "description": "22000rs flight price ",
      "date": "2023-04-18",
      "priority": "High",
      "status": "Todo",
      "owner": "(IA)",
      "id": 27
    },
    {
      "title": "Hotel Booking",
      "description": "done",
      "date": "2023-04-18",
      "priority": "High",
      "status": "Todo",
      "owner": "(IA)",
      "id": 28
    },
    {
      "title": "Scooty",
      "description": "per day",
      "date": "2023-04-18",
      "priority": "High",
      "status": "Todo",
      "owner": "(IA)",
      "id": 29
    },
    {
      "title": "Food ",
      "description": "per person",
      "date": "2023-04-18",
      "priority": "High",
      "status": "Todo",
      "owner": "(IA)",
      "id": 30
    },
    {
      "title": "return flight",
      "description": "return",
      "date": "2023-04-18",
      "priority": "High",
      "status": "Todo",
      "owner": "IA",
      "id": 31
    },
    {
      "title": "play",
      "description": "ground",
      "date": "2024-03-15",
      "priority": "Medium",
      "status": "In-Progress",
      "owner": "ritesh",
      "id": 32
    },
    {
      "title": "dance",
      "description": "floor",
      "date": "2024-03-15",
      "priority": "Medium",
      "status": "In-Progress",
      "owner": "dj",
      "id": 33
    },
    {
      "title": "fsdfsdgdf",
      "description": "hfhfhfgjghg",
      "date": "2023-02-22",
      "priority": "Medium",
      "status": "Review",
      "owner": "My name is Jhon cina",
      "id": 22
    },
    {
      "title": "play",
      "description": "game",
      "date": "2024-03-15",
      "priority": "Low",
      "status": "Review",
      "owner": "don",
      "id": 34
    }
  ]
}